kuzco/__init__.py
kuzco/cli/__init__.py
kuzco/cli/cli.py
kuzco/core/__init__.py
kuzco/core/case_manager.py
kuzco/core/ci_manager.py
kuzco/core/creator_manager.py
kuzco/core/pip_manager.py
kuzco/core/run_manager.py
kuzco/core/rundebug_manager.py
kuzco/core/venv_manager.py
kuzco/core/watch_local.py
kuzco/helpers/__init__.py
kuzco/helpers/logger.py
kuzco/scripts/__init__.py
kuzco/scripts/tree.py
kuzco-0.1.19.dist-info/METADATA
kuzco-0.1.19.dist-info/WHEEL
kuzco-0.1.19.dist-info/entry_points.txt
kuzco-0.1.19.dist-info/top_level.txt
kuzco-0.1.19.dist-info/RECORD
