Metadata-Version: 2.1
Name: kuzco
Version: 0.1.19
Summary: Tool for managing Python monorepos
Home-page: https://gitlab.com/yakov.perets/kuzco
Author: Yakov Perets
Author-email: yakov.perets@gmail.com
Classifier: Programming Language :: Python :: 3
Classifier: License :: OSI Approved :: MIT License
Classifier: Operating System :: OS Independent
Requires-Python: >=3.6
Requires-Dist: click
Requires-Dist: watchdog
